<annotation>
	<folder></folder>
	<filename>frame2718_jpg.rf.b91925c774d9b50f50a727410f1e064a.jpg</filename>
	<path>frame2718_jpg.rf.b91925c774d9b50f50a727410f1e064a.jpg</path>
	<source>
		<database>roboflow.com</database>
	</source>
	<size>
		<width>640</width>
		<height>640</height>
		<depth>3</depth>
	</size>
	<segmented>0</segmented>
	<object>
		<name>thermal_defect</name>
		<pose>Unspecified</pose>
		<truncated>0</truncated>
		<difficult>0</difficult>
		<occluded>0</occluded>
		<bndbox>
			<xmin>409</xmin>
			<xmax>452</xmax>
			<ymin>414</ymin>
			<ymax>505</ymax>
		</bndbox>
	</object>
	<object>
		<name>thermal_defect</name>
		<pose>Unspecified</pose>
		<truncated>0</truncated>
		<difficult>0</difficult>
		<occluded>0</occluded>
		<bndbox>
			<xmin>340</xmin>
			<xmax>384</xmax>
			<ymin>111</ymin>
			<ymax>194</ymax>
		</bndbox>
	</object>
</annotation>
