<annotation>
	<folder></folder>
	<filename>IMGT0239_PNG_jpg.rf.556c8dae8db5f985c446059dc9f304a7.jpg</filename>
	<path>IMGT0239_PNG_jpg.rf.556c8dae8db5f985c446059dc9f304a7.jpg</path>
	<source>
		<database>roboflow.com</database>
	</source>
	<size>
		<width>640</width>
		<height>640</height>
		<depth>3</depth>
	</size>
	<segmented>0</segmented>
	<object>
		<name>thermal_defect</name>
		<pose>Unspecified</pose>
		<truncated>0</truncated>
		<difficult>0</difficult>
		<occluded>0</occluded>
		<bndbox>
			<xmin>62</xmin>
			<xmax>554</xmax>
			<ymin>10</ymin>
			<ymax>309</ymax>
		</bndbox>
		<polygon>
			<x1>96.578296</x1>
			<y1>307.859518</y1>
			<x2>444.652862</x2>
			<y2>301.739215</y2>
			<x3>552.413446</x3>
			<y3>14.380583</y3>
			<x4>552.916479</x4>
			<y4>8.588647</y4>
			<x5>61.483355</x5>
			<y5>16.740143</y5>
			<x6>96.578296</x6>
			<y6>307.859518</y6>
		</polygon>
	</object>
</annotation>
