<annotation>
	<folder></folder>
	<filename>image_0_1313_jpeg_jpg.rf.dda9d742538fd86dc023104e6c521df8.jpg</filename>
	<path>image_0_1313_jpeg_jpg.rf.dda9d742538fd86dc023104e6c521df8.jpg</path>
	<source>
		<database>roboflow.com</database>
	</source>
	<size>
		<width>640</width>
		<height>640</height>
		<depth>3</depth>
	</size>
	<segmented>0</segmented>
	<object>
		<name>thermal_defect</name>
		<pose>Unspecified</pose>
		<truncated>0</truncated>
		<difficult>0</difficult>
		<occluded>0</occluded>
		<bndbox>
			<xmin>254</xmin>
			<xmax>372</xmax>
			<ymin>343</ymin>
			<ymax>508</ymax>
		</bndbox>
		<polygon>
			<x1>350.31056</x1>
			<y1>341.614906</y1>
			<x2>253.416149</x2>
			<y2>341.614906</y2>
			<x3>258.385094</x3>
			<y3>506.832297</y3>
			<x4>371.428571</x4>
			<y4>505.590063</y4>
			<x5>350.31056</x5>
			<y5>341.614906</y5>
		</polygon>
	</object>
	<object>
		<name>thermal_defect</name>
		<pose>Unspecified</pose>
		<truncated>0</truncated>
		<difficult>0</difficult>
		<occluded>0</occluded>
		<bndbox>
			<xmin>134</xmin>
			<xmax>247</xmax>
			<ymin>208</ymin>
			<ymax>338</ymax>
		</bndbox>
		<polygon>
			<x1>243.47826</x1>
			<y1>207.453417</y1>
			<x2>146.583851</x2>
			<y2>207.453417</y2>
			<x3>132.919254</x3>
			<y3>336.645963</y3>
			<x4>245.962734</x4>
			<y4>332.919254</y4>
			<x5>243.47826</x5>
			<y5>207.453417</y5>
		</polygon>
	</object>
	<object>
		<name>thermal_defect</name>
		<pose>Unspecified</pose>
		<truncated>0</truncated>
		<difficult>0</difficult>
		<occluded>0</occluded>
		<bndbox>
			<xmin>248</xmin>
			<xmax>354</xmax>
			<ymin>204</ymin>
			<ymax>336</ymax>
		</bndbox>
	</object>
	<object>
		<name>thermal_defect</name>
		<pose>Unspecified</pose>
		<truncated>0</truncated>
		<difficult>0</difficult>
		<occluded>0</occluded>
		<bndbox>
			<xmin>453</xmin>
			<xmax>577</xmax>
			<ymin>200</ymin>
			<ymax>341</ymax>
		</bndbox>
		<polygon>
			<x1>452.173914</x1>
			<y1>202.484471</y1>
			<x2>470.807454</x2>
			<y2>340.372671</y2>
			<x3>576.397514</x3>
			<y3>331.67702</y3>
			<x4>541.614906</x4>
			<y4>198.757763</y4>
			<x5>452.173914</x5>
			<y5>202.484471</y5>
		</polygon>
	</object>
	<object>
		<name>thermal_defect</name>
		<pose>Unspecified</pose>
		<truncated>0</truncated>
		<difficult>0</difficult>
		<occluded>0</occluded>
		<bndbox>
			<xmin>350</xmin>
			<xmax>476</xmax>
			<ymin>200</ymin>
			<ymax>334</ymax>
		</bndbox>
		<polygon>
			<x1>349.068323</x1>
			<y1>198.757763</y1>
			<x2>360.248449</x2>
			<y2>332.919254</y2>
			<x3>474.534163</x3>
			<y3>331.67702</y3>
			<x4>449.68944</x4>
			<y4>200</y4>
			<x5>349.068323</x5>
			<y5>198.757763</y5>
		</polygon>
	</object>
	<object>
		<name>thermal_defect</name>
		<pose>Unspecified</pose>
		<truncated>0</truncated>
		<difficult>0</difficult>
		<occluded>0</occluded>
		<bndbox>
			<xmin>247</xmin>
			<xmax>343</xmax>
			<ymin>98</ymin>
			<ymax>203</ymax>
		</bndbox>
	</object>
	<object>
		<name>thermal_defect</name>
		<pose>Unspecified</pose>
		<truncated>0</truncated>
		<difficult>0</difficult>
		<occluded>0</occluded>
		<bndbox>
			<xmin>343</xmin>
			<xmax>446</xmax>
			<ymin>94</ymin>
			<ymax>201</ymax>
		</bndbox>
		<polygon>
			<x1>428.571429</x1>
			<y1>94.409937</y1>
			<x2>341.614906</x2>
			<y2>93.167703</y2>
			<x3>347.826086</x3>
			<y3>200</y3>
			<x4>444.720497</x4>
			<y4>198.757763</y4>
			<x5>428.571429</x5>
			<y5>94.409937</y5>
		</polygon>
	</object>
	<object>
		<name>thermal_defect</name>
		<pose>Unspecified</pose>
		<truncated>0</truncated>
		<difficult>0</difficult>
		<occluded>0</occluded>
		<bndbox>
			<xmin>433</xmin>
			<xmax>545</xmax>
			<ymin>92</ymin>
			<ymax>201</ymax>
		</bndbox>
		<polygon>
			<x1>516.770186</x1>
			<y1>90.683229</y1>
			<x2>432.298137</x2>
			<y2>96.894409</y2>
			<x3>453.416149</x3>
			<y3>196.273291</y3>
			<x4>544.09938</x4>
			<y4>200</y4>
			<x5>516.770186</x5>
			<y5>90.683229</y5>
		</polygon>
	</object>
	<object>
		<name>thermal_defect</name>
		<pose>Unspecified</pose>
		<truncated>0</truncated>
		<difficult>0</difficult>
		<occluded>0</occluded>
		<bndbox>
			<xmin>148</xmin>
			<xmax>244</xmax>
			<ymin>94</ymin>
			<ymax>208</ymax>
		</bndbox>
		<polygon>
			<x1>243.47826</x1>
			<y1>93.167703</y1>
			<x2>156.52174</x2>
			<y2>94.409937</y2>
			<x3>146.583851</x3>
			<y3>203.726709</y3>
			<x4>243.47826</x4>
			<y4>207.453417</y4>
			<x5>243.47826</x5>
			<y5>93.167703</y5>
		</polygon>
	</object>
	<object>
		<name>thermal_defect</name>
		<pose>Unspecified</pose>
		<truncated>0</truncated>
		<difficult>0</difficult>
		<occluded>0</occluded>
		<bndbox>
			<xmin>500</xmin>
			<xmax>608</xmax>
			<ymin>1</ymin>
			<ymax>92</ymax>
		</bndbox>
		<polygon>
			<x1>499.378883</x1>
			<y1>3.726709</y1>
			<x2>519.254657</x2>
			<y2>90.683229</y2>
			<x3>607.453417</x3>
			<y3>86.956523</y3>
			<x4>578.881989</x4>
			<y4>0</y4>
			<x5>499.378883</x5>
			<y5>3.726709</y5>
		</polygon>
	</object>
	<object>
		<name>thermal_defect</name>
		<pose>Unspecified</pose>
		<truncated>0</truncated>
		<difficult>0</difficult>
		<occluded>0</occluded>
		<bndbox>
			<xmin>422</xmin>
			<xmax>520</xmax>
			<ymin>2</ymin>
			<ymax>97</ymax>
		</bndbox>
		<polygon>
			<x1>519.254657</x1>
			<y1>95.652174</y1>
			<x2>496.894409</x2>
			<y2>3.726709</y2>
			<x3>496.894409</x3>
			<y3>1.242237</y3>
			<x4>421.118011</x4>
			<y4>2.484471</y4>
			<x5>431.0559</x5>
			<y5>93.167703</y5>
			<x6>519.254657</x6>
			<y6>95.652174</y6>
		</polygon>
	</object>
	<object>
		<name>thermal_defect</name>
		<pose>Unspecified</pose>
		<truncated>0</truncated>
		<difficult>0</difficult>
		<occluded>0</occluded>
		<bndbox>
			<xmin>334</xmin>
			<xmax>427</xmax>
			<ymin>3</ymin>
			<ymax>89</ymax>
		</bndbox>
		<polygon>
			<x1>342.857143</x1>
			<y1>88.198757</y1>
			<x2>426.086957</x2>
			<y2>88.198757</y2>
			<x3>414.906831</x3>
			<y3>2.484471</y3>
			<x4>332.919254</x4>
			<y4>4.968943</y4>
			<x5>342.857143</x5>
			<y5>88.198757</y5>
		</polygon>
	</object>
	<object>
		<name>thermal_defect</name>
		<pose>Unspecified</pose>
		<truncated>0</truncated>
		<difficult>0</difficult>
		<occluded>0</occluded>
		<bndbox>
			<xmin>156</xmin>
			<xmax>246</xmax>
			<ymin>1</ymin>
			<ymax>90</ymax>
		</bndbox>
		<polygon>
			<x1>156.52174</x1>
			<y1>89.440994</y1>
			<x2>244.720497</x2>
			<y2>89.440994</y2>
			<x3>244.720497</x3>
			<y3>0</y3>
			<x4>155.279503</x4>
			<y4>2.484471</y4>
			<x5>156.52174</x5>
			<y5>89.440994</y5>
		</polygon>
	</object>
</annotation>
