<annotation>
	<folder></folder>
	<filename>img-431-_JPG_jpg.rf.bb9ed8ff79b5dc8204efd83b09662dfe.jpg</filename>
	<path>img-431-_JPG_jpg.rf.bb9ed8ff79b5dc8204efd83b09662dfe.jpg</path>
	<source>
		<database>roboflow.com</database>
	</source>
	<size>
		<width>640</width>
		<height>640</height>
		<depth>3</depth>
	</size>
	<segmented>0</segmented>
	<object>
		<name>thermal_defect</name>
		<pose>Unspecified</pose>
		<truncated>0</truncated>
		<difficult>0</difficult>
		<occluded>0</occluded>
		<bndbox>
			<xmin>180</xmin>
			<xmax>262</xmax>
			<ymin>54</ymin>
			<ymax>123</ymax>
		</bndbox>
	</object>
	<object>
		<name>thermal_defect</name>
		<pose>Unspecified</pose>
		<truncated>0</truncated>
		<difficult>0</difficult>
		<occluded>0</occluded>
		<bndbox>
			<xmin>171</xmin>
			<xmax>255</xmax>
			<ymin>205</ymin>
			<ymax>290</ymax>
		</bndbox>
	</object>
	<object>
		<name>thermal_defect</name>
		<pose>Unspecified</pose>
		<truncated>0</truncated>
		<difficult>0</difficult>
		<occluded>0</occluded>
		<bndbox>
			<xmin>165</xmin>
			<xmax>251</xmax>
			<ymin>291</ymin>
			<ymax>384</ymax>
		</bndbox>
	</object>
	<object>
		<name>thermal_defect</name>
		<pose>Unspecified</pose>
		<truncated>0</truncated>
		<difficult>0</difficult>
		<occluded>0</occluded>
		<bndbox>
			<xmin>159</xmin>
			<xmax>248</xmax>
			<ymin>379</ymin>
			<ymax>479</ymax>
		</bndbox>
	</object>
	<object>
		<name>thermal_defect</name>
		<pose>Unspecified</pose>
		<truncated>0</truncated>
		<difficult>0</difficult>
		<occluded>0</occluded>
		<bndbox>
			<xmin>246</xmin>
			<xmax>339</xmax>
			<ymin>373</ymin>
			<ymax>473</ymax>
		</bndbox>
	</object>
</annotation>
