<annotation>
	<folder></folder>
	<filename>BAKERELECTRICBLOCK18-23_100MEDIA_0499_1_JPG_jpg.rf.405e6d3522ca34ae276f2bf2a15b9525.jpg</filename>
	<path>BAKERELECTRICBLOCK18-23_100MEDIA_0499_1_JPG_jpg.rf.405e6d3522ca34ae276f2bf2a15b9525.jpg</path>
	<source>
		<database>roboflow.com</database>
	</source>
	<size>
		<width>640</width>
		<height>640</height>
		<depth>3</depth>
	</size>
	<segmented>0</segmented>
	<object>
		<name>thermal_defect</name>
		<pose>Unspecified</pose>
		<truncated>0</truncated>
		<difficult>0</difficult>
		<occluded>0</occluded>
		<bndbox>
			<xmin>103</xmin>
			<xmax>129</xmax>
			<ymin>194</ymin>
			<ymax>231</ymax>
		</bndbox>
	</object>
	<object>
		<name>thermal_defect</name>
		<pose>Unspecified</pose>
		<truncated>0</truncated>
		<difficult>0</difficult>
		<occluded>0</occluded>
		<bndbox>
			<xmin>85</xmin>
			<xmax>107</xmax>
			<ymin>196</ymin>
			<ymax>235</ymax>
		</bndbox>
	</object>
</annotation>
